topsis/__init__.py
topsis/__main__.py
topsis_sarvagyjain_102003553-1.0.1.dist-info/LICENSE.txt
topsis_sarvagyjain_102003553-1.0.1.dist-info/METADATA
topsis_sarvagyjain_102003553-1.0.1.dist-info/WHEEL
topsis_sarvagyjain_102003553-1.0.1.dist-info/entry_points.txt
topsis_sarvagyjain_102003553-1.0.1.dist-info/top_level.txt
topsis_sarvagyjain_102003553-1.0.1.dist-info/RECORD
