Metadata-Version: 2.1
Name: topsis-sarvagyjain-102003553
Version: 1.0.1
Summary: A Python package to find TOPSIS for multi-criteria decision analysis method
Home-page: https://github.com/Sarvagy-Jain/topsis_python_package
Author: Sarvagy Jain
Author-email: sjain_be20@thapar.edu
License: MIT
Keywords: UCS654,TIET
License-File: LICENSE.txt
Requires-Dist: pandas
Requires-Dist: tabulate
